{
	"video_id": "c3p1ypeqfmorfwwy2ypcrigm",
	"slug": "hands-on-introduction-to-acorn",
	"title": "Hands-on Introduction to Acorn",
	"generated_at": "2026-05-17T13:25:33.719Z",
	"known_technology_names": [
		"Acorn"
	],
	"known_guest_names": [
		"Darren Shepherd"
	],
	"resources": [
		{
			"title": "Acorn getting started guide",
			"category": "documentation",
			"evidence_quote": "this is actually the app from our getting started guide",
			"confidence": "high"
		},
		{
			"title": "Jenkins on Acorn example",
			"category": "demos",
			"evidence_quote": "somebody had asked me for a Jenkins, to do, what would it look like to run Jenkins and Acorn.",
			"confidence": "medium"
		}
	]
}
