{
	"video_id": "xgp6tiusatvjqsse8tour3hl",
	"slug": "klustered-16",
	"title": "Klustered #16",
	"generated_at": "2026-05-17T13:20:44.439Z",
	"known_technology_names": [],
	"known_guest_names": [
		"Rachel Leekin",
		"Andy Holtzmann",
		"Andy Holtzmann"
	],
	"resources": [
		{
			"title": "Rawkode Academy Discord server",
			"category": "other",
			"evidence_quote": "you can join us on the Discord server available at Rawkode.chat.",
			"confidence": "medium"
		},
		{
			"title": "Teleport sponsor link",
			"category": "other",
			"evidence_quote": "Please check out Rawkode.liveteleport",
			"confidence": "medium"
		}
	]
}
